LangaraCourseInfo.py
parsers/AttributesParser.py
parsers/CatalogueParser.py
parsers/SemesterParser.py
parsers/TransferParser.py
schema/Attribute.py
schema/Catalogue.py
schema/CourseInfo.py
schema/Semester.py
schema/Transfer.py
scrapers/DownloadLangaraInfo.py
scrapers/DownloadTransferInfo.py
scrapers/DownloadTransferInfo2.py
LangaraCourseInfo-2.0.0.dist-info/METADATA
LangaraCourseInfo-2.0.0.dist-info/WHEEL
LangaraCourseInfo-2.0.0.dist-info/top_level.txt
LangaraCourseInfo-2.0.0.dist-info/RECORD
