Metadata-Version: 2.1
Name: LangaraCourseInfo
Version: 2.0.0
Summary: Langara Course Information Aggregator
Author-email: Anderson T <tseng.andersonn@gmail.com>
Project-URL: Homepage, https://github.com/Highfire1/LangaraCourseInfo
Keywords: langara,college,scraper,data
Classifier: Programming Language :: Python
Classifier: Programming Language :: Python :: 3
Requires-Python: >=3.9
Requires-Dist: bs4
Requires-Dist: lxml
Requires-Dist: faust-cchardet
Requires-Dist: requests
Requires-Dist: pdfquery
Requires-Dist: pymupdf
Requires-Dist: pydantic
Requires-Dist: six
Requires-Dist: selenium
Requires-Dist: tomli ; python_version < "3.11"
Provides-Extra: dev
Requires-Dist: black ; extra == 'dev'
Requires-Dist: bumpver ; extra == 'dev'
Requires-Dist: isort ; extra == 'dev'
Requires-Dist: pip-tools ; extra == 'dev'
Requires-Dist: pytest ; extra == 'dev'
